scales/__init__.py
scales/exceptions.py
scales/scales.py
scales/utilities.py
scales_mer725_driver-0.1.3.dist-info/licenses/LICENSE
scales_mer725_driver-0.1.3.dist-info/METADATA
scales_mer725_driver-0.1.3.dist-info/WHEEL
scales_mer725_driver-0.1.3.dist-info/top_level.txt
scales_mer725_driver-0.1.3.dist-info/RECORD
