Metadata-Version: 2.4
Name: scales-mer725-driver
Version: 0.1.3
Summary: Python library for interacting with Mertech M-ER 725 scales over TCP
Author: Nikita Chepelskiy
License: MIT License
Project-URL: Homepage, https://github.com/Zazikni/scales-mer725-driver
Project-URL: Repository, https://github.com/Zazikni/scales-mer725-driver
Project-URL: Issues, https://github.com/Zazikni/scales-mer725-driver/issues
Keywords: mertech,scales,m-er-725,retail,json
Classifier: Programming Language :: Python :: 3
Classifier: Programming Language :: Python :: 3 :: Only
Classifier: License :: OSI Approved :: MIT License
Classifier: Operating System :: OS Independent
Classifier: Topic :: Software Development :: Libraries
Classifier: Topic :: System :: Networking
Requires-Python: >=3.10
License-File: LICENSE
Dynamic: license-file
